map2gpt/__init__.py
map2gpt/deploy.py
map2gpt/log.py
map2gpt/main.py
map2gpt/model.py
map2gpt/runner.py
map2gpt/strategies.py
map2gpt/telegram_bot.py
map2gpt/examples/from_text_files.py
map2gpt-0.2.0.dist-info/LICENSE
map2gpt-0.2.0.dist-info/METADATA
map2gpt-0.2.0.dist-info/WHEEL
map2gpt-0.2.0.dist-info/top_level.txt
map2gpt-0.2.0.dist-info/RECORD
