Metadata-Version: 2.1
Name: map2gpt
Version: 0.2.0
Summary: A python package to index and search documents using GPT3
Author-email: Ibrahima BA <ibrahima.elmokhtar@gmail.com>
Project-URL: Homepage, https://github.com/milkymap/map2gpt
Keywords: GPT3, gpt-index, llama-index, pdf2gpt, doc2gpt, wikipedia2gpt, semantic-search
Classifier: Programming Language :: Python :: 3
Classifier: License :: OSI Approved :: MIT License
Classifier: Operating System :: OS Independent
Requires-Python: >=3.7
License-File: LICENSE
Requires-Dist: click
Requires-Dist: wikipedia
Requires-Dist: pytube
Requires-Dist: pydub
Requires-Dist: openai
Requires-Dist: tiktoken
Requires-Dist: httpx
Requires-Dist: torch
Requires-Dist: numpy
Requires-Dist: protobuf (<=3.19.0)
Requires-Dist: sentence-transformers
Requires-Dist: PyPDF2
Requires-Dist: qdrant-client
Requires-Dist: pydantic
Requires-Dist: python-telegram-bot
Requires-Dist: tenacity
